jsno/__init__.py
jsno/abc.py
jsno/constraint.py
jsno/datetime.py
jsno/extra_data.py
jsno/fields_unjsonifier.py
jsno/jsonify.py
jsno/jsonize.py
jsno/method.py
jsno/property_name.py
jsno/schema.py
jsno/standard.py
jsno/tuple.py
jsno/typeddict.py
jsno/unjsonify.py
jsno/utils.py
jsno/variant.py
jsno-1.3.0.dist-info/licenses/LICENSE
jsno-1.3.0.dist-info/METADATA
jsno-1.3.0.dist-info/WHEEL
jsno-1.3.0.dist-info/top_level.txt
jsno-1.3.0.dist-info/RECORD
