Metadata-Version: 2.4
Name: jsno
Version: 1.3.0
Summary: Convert Python data to and from json-compatible data structures
License-Expression: MIT
Project-URL: Homepage, https://github.com/pek/jsno
Keywords: json
Classifier: Programming Language :: Python
Classifier: Programming Language :: Python :: 3
Requires-Python: >=3.11
License-File: LICENSE
Provides-Extra: dev
Requires-Dist: pytest; extra == "dev"
Requires-Dist: coverage; extra == "dev"
Dynamic: license-file
